MANIFEST.in
README.rst
setup.py
collective/__init__.py
collective.jqcookie.egg-info/PKG-INFO
collective.jqcookie.egg-info/SOURCES.txt
collective.jqcookie.egg-info/dependency_links.txt
collective.jqcookie.egg-info/entry_points.txt
collective.jqcookie.egg-info/namespace_packages.txt
collective.jqcookie.egg-info/not-zip-safe
collective.jqcookie.egg-info/requires.txt
collective.jqcookie.egg-info/top_level.txt
collective/jqcookie/__init__.py
collective/jqcookie/configure.zcml
collective/jqcookie/jquery.cookie.js
collective/jqcookie/profiles/default/jsregistry.xml
collective/jqcookie/profiles/default/metadata.xml
docs/HISTORY.txt
docs/LICENSE.GPL
docs/LICENSE.txt