Metadata-Version: 1.0
Name: collective.jqcookie
Version: 1.1.0
Summary: Collective jqcookie Package (Maintainer: Victor baumann)
Home-page: https://github.com/4teamwork/collective.jqcookie
Author: Victor baumann
Author-email: mailto:info@4teamwork.ch
License: GPL
Keywords: jquery cookie 4teamwork
Platform: UNKNOWN
Classifier: Framework :: Plone
Classifier: Framework :: Plone :: 4.0
Classifier: Framework :: Plone :: 4.1
Classifier: Framework :: Plone :: 4.2
Classifier: Framework :: Plone :: 4.3
Classifier: Intended Audience :: Developers
Classifier: Programming Language :: Python
Classifier: Topic :: Software Development :: Libraries :: Python Modules
